faas_sdk_python/__init__.py
faas_sdk_python/__main__.py
faas_sdk_python/_cli.py
faas_sdk_python/_function_registry.py
faas_sdk_python/exceptions.py
faas_sdk_python-1.0.1.dist-info/LICENSE
faas_sdk_python-1.0.1.dist-info/METADATA
faas_sdk_python-1.0.1.dist-info/WHEEL
faas_sdk_python-1.0.1.dist-info/entry_points.txt
faas_sdk_python-1.0.1.dist-info/top_level.txt
faas_sdk_python-1.0.1.dist-info/RECORD
