Metadata-Version: 2.1
Name: faas-sdk-python
Version: 1.0.1
Summary: An open source FaaS (Function as a service) sdk for Sber Platform V functions local testing & running
Home-page: https://github.com/sber-platformv/faas-sdk-python
Author: Sber
Author-email: developers@sber.ru
Keywords: faas-sdk-python
Classifier: Development Status :: 3 - Alpha
Classifier: Intended Audience :: Developers
Classifier: License :: OSI Approved :: Apache Software License
Classifier: Programming Language :: Python :: 3
Classifier: Programming Language :: Python :: 3.8
Classifier: Programming Language :: Python :: 3.9
Classifier: Programming Language :: Python :: 3.10
Requires-Python: >=3.8, <4
License-File: LICENSE
Requires-Dist: flask (<3.0,>=2.0)
Requires-Dist: click (<9.0,>=7.0)
